qself/__init__.py
qself/_modidx.py
qself/oura.py
qself-0.0.3.dist-info/LICENSE
qself-0.0.3.dist-info/METADATA
qself-0.0.3.dist-info/WHEEL
qself-0.0.3.dist-info/entry_points.txt
qself-0.0.3.dist-info/top_level.txt
qself-0.0.3.dist-info/RECORD
