Metadata-Version: 2.1
Name: qself
Version: 0.0.3
Summary: Tools to extract personal, quantitative data from various sources.
Home-page: https://github.com/JungeAlexander/qself
Author: Alexander Junge
Author-email: alexander.junge@gmail.com
License: Apache Software License 2.0
Keywords: nbdev jupyter notebook python
Classifier: Development Status :: 4 - Beta
Classifier: Intended Audience :: Developers
Classifier: Natural Language :: English
Classifier: Programming Language :: Python :: 3.10
Classifier: License :: OSI Approved :: Apache Software License
Requires-Python: >=3.10
License-File: LICENSE
Requires-Dist: python-dotenv
Requires-Dist: pandas
Requires-Dist: requests
Provides-Extra: dev
